{
  "signals": [
    {
      "id": "2026-05-18-0938-NIFTY-23350-PE",
      "date": "2026-05-18",
      "time": "09:38:19",
      "type": "OPTION",
      "stock": "NIFTY",
      "name": "NIFTY 23350 PE",
      "signal": "BUY",
      "confidence": 84,
      "strength": "STRONG",
      "numInds": 9,
      "entry": 124.4,
      "sl": 93.3,
      "target": 161.72,
      "strike": 23350,
      "optType": "PE",
      "expiry": "2026-05-19",
      "lot": 75,
      "delta": -0.4728,
      "iv": 24.93,
      "trendAligned": true,
      "capitalReq": 9330,
      "rr": 1.2,
      "winRateEst": 55,
      "vix": 19.95,
      "slTgtMethod": "IV 25% | DTE 1 | Delta 0.47",
      "compositeScore": -0.6,
      "momentumScore": null,
      "emaCross": null,
      "priceZone": "belowPDL",
      "status": "OPEN",
      "exitPrice": null,
      "exitTime": null,
      "pnlPct": null,
      "note": ""
    },
    {
      "id": "2026-05-18-0938-NIFTY-23200-PE",
      "date": "2026-05-18",
      "time": "09:38:19",
      "type": "OPTION",
      "stock": "NIFTY",
      "name": "NIFTY 23200 PE",
      "signal": "BUY",
      "confidence": 80,
      "strength": "STRONG",
      "numInds": 8,
      "entry": 68.6,
      "sl": 51.45,
      "target": 89.18,
      "strike": 23200,
      "optType": "PE",
      "expiry": "2026-05-19",
      "lot": 75,
      "delta": -0.3083,
      "iv": 25.45,
      "trendAligned": true,
      "capitalReq": 5145,
      "rr": 1.2,
      "winRateEst": 55,
      "vix": 19.95,
      "slTgtMethod": "IV 25% | DTE 1 | Delta 0.31",
      "compositeScore": -0.6,
      "momentumScore": null,
      "emaCross": null,
      "priceZone": "belowPDL",
      "status": "OPEN",
      "exitPrice": null,
      "exitTime": null,
      "pnlPct": null,
      "note": ""
    },
    {
      "id": "2026-05-18-0938-NIFTY-23250-PE",
      "date": "2026-05-18",
      "time": "09:38:19",
      "type": "OPTION",
      "stock": "NIFTY",
      "name": "NIFTY 23250 PE",
      "signal": "BUY",
      "confidence": 80,
      "strength": "STRONG",
      "numInds": 8,
      "entry": 84.5,
      "sl": 59.15,
      "target": 114.92,
      "strike": 23250,
      "optType": "PE",
      "expiry": "2026-05-19",
      "lot": 75,
      "delta": -0.3599,
      "iv": 25.25,
      "trendAligned": true,
      "capitalReq": 6338,
      "rr": 1.2,
      "winRateEst": 55,
      "vix": 19.95,
      "slTgtMethod": "IV 25% | DTE 1 | Delta 0.36",
      "compositeScore": -0.6,
      "momentumScore": null,
      "emaCross": null,
      "priceZone": "belowPDL",
      "status": "OPEN",
      "exitPrice": null,
      "exitTime": null,
      "pnlPct": null,
      "note": ""
    },
    {
      "id": "2026-05-18-0938-NIFTY-23300-PE",
      "date": "2026-05-18",
      "time": "09:38:19",
      "type": "OPTION",
      "stock": "NIFTY",
      "name": "NIFTY 23300 PE",
      "signal": "BUY",
      "confidence": 80,
      "strength": "STRONG",
      "numInds": 8,
      "entry": 103.2,
      "sl": 72.24,
      "target": 140.35,
      "strike": 23300,
      "optType": "PE",
      "expiry": "2026-05-19",
      "lot": 75,
      "delta": -0.4149,
      "iv": 25.01,
      "trendAligned": true,
      "capitalReq": 7740,
      "rr": 1.2,
      "winRateEst": 55,
      "vix": 19.95,
      "slTgtMethod": "IV 25% | DTE 1 | Delta 0.41",
      "compositeScore": -0.6,
      "momentumScore": null,
      "emaCross": null,
      "priceZone": "belowPDL",
      "status": "OPEN",
      "exitPrice": null,
      "exitTime": null,
      "pnlPct": null,
      "note": ""
    },
    {
      "id": "2026-05-18-0938-NIFTY-23150-PE",
      "date": "2026-05-18",
      "time": "09:38:19",
      "type": "OPTION",
      "stock": "NIFTY",
      "name": "NIFTY 23150 PE",
      "signal": "WATCH",
      "confidence": 75,
      "strength": "STRONG",
      "numInds": 5,
      "entry": 55.35,
      "sl": 41.51,
      "target": 71.96,
      "strike": 23150,
      "optType": "PE",
      "expiry": "2026-05-19",
      "lot": 75,
      "delta": -0.2606,
      "iv": 25.63,
      "trendAligned": true,
      "capitalReq": 4151,
      "rr": 1.2,
      "winRateEst": 55,
      "vix": 19.95,
      "slTgtMethod": "IV 26% | DTE 1 | Delta 0.26",
      "compositeScore": -0.6,
      "momentumScore": null,
      "emaCross": null,
      "priceZone": "belowPDL",
      "status": "OPEN",
      "exitPrice": null,
      "exitTime": null,
      "pnlPct": null,
      "note": ""
    },
    {
      "id": "2026-05-18-0938-NIFTY-23050-PE",
      "date": "2026-05-18",
      "time": "09:38:19",
      "type": "OPTION",
      "stock": "NIFTY",
      "name": "NIFTY 23050 PE",
      "signal": "WATCH",
      "confidence": 74,
      "strength": "MODERATE",
      "numInds": 5,
      "entry": 35.1,
      "sl": 26.33,
      "target": 45.62,
      "strike": 23050,
      "optType": "PE",
      "expiry": "2026-05-19",
      "lot": 75,
      "delta": -0.181,
      "iv": 26.18,
      "trendAligned": true,
      "capitalReq": 2633,
      "rr": 1.2,
      "winRateEst": 55,
      "vix": 19.95,
      "slTgtMethod": "IV 26% | DTE 1 | Delta 0.18",
      "compositeScore": -0.6,
      "momentumScore": null,
      "emaCross": null,
      "priceZone": "belowPDL",
      "status": "OPEN",
      "exitPrice": null,
      "exitTime": null,
      "pnlPct": null,
      "note": ""
    },
    {
      "id": "2026-05-18-0938-NIFTY-23100-PE",
      "date": "2026-05-18",
      "time": "09:38:19",
      "type": "OPTION",
      "stock": "NIFTY",
      "name": "NIFTY 23100 PE",
      "signal": "WATCH",
      "confidence": 74,
      "strength": "MODERATE",
      "numInds": 5,
      "entry": 44.25,
      "sl": 33.19,
      "target": 57.52,
      "strike": 23100,
      "optType": "PE",
      "expiry": "2026-05-19",
      "lot": 75,
      "delta": -0.2189,
      "iv": 25.97,
      "trendAligned": true,
      "capitalReq": 3319,
      "rr": 1.2,
      "winRateEst": 55,
      "vix": 19.95,
      "slTgtMethod": "IV 26% | DTE 1 | Delta 0.22",
      "compositeScore": -0.6,
      "momentumScore": null,
      "emaCross": null,
      "priceZone": "belowPDL",
      "status": "OPEN",
      "exitPrice": null,
      "exitTime": null,
      "pnlPct": null,
      "note": ""
    },
    {
      "id": "2026-05-18-0938-SENSEX-73600-PE",
      "date": "2026-05-18",
      "time": "09:38:19",
      "type": "OPTION",
      "stock": "SENSEX",
      "name": "SENSEX 73600 PE",
      "signal": "BUY",
      "confidence": 84,
      "strength": "STRONG",
      "numInds": 8,
      "entry": 355,
      "sl": 266.25,
      "target": 488.13,
      "strike": 73600,
      "optType": "PE",
      "expiry": "2026-05-21",
      "lot": 20,
      "delta": -0.3179,
      "iv": 24.22,
      "trendAligned": true,
      "capitalReq": 7100,
      "rr": 1.5,
      "winRateEst": 55,
      "vix": 19.95,
      "slTgtMethod": "IV 24% | DTE 3 | Delta 0.32",
      "compositeScore": -0.6,
      "momentumScore": null,
      "emaCross": null,
      "priceZone": "belowPDL",
      "status": "OPEN",
      "exitPrice": null,
      "exitTime": null,
      "pnlPct": null,
      "note": ""
    },
    {
      "id": "2026-05-18-0938-SENSEX-73700-PE",
      "date": "2026-05-18",
      "time": "09:38:19",
      "type": "OPTION",
      "stock": "SENSEX",
      "name": "SENSEX 73700 PE",
      "signal": "BUY",
      "confidence": 84,
      "strength": "STRONG",
      "numInds": 8,
      "entry": 386.65,
      "sl": 289.99,
      "target": 531.64,
      "strike": 73700,
      "optType": "PE",
      "expiry": "2026-05-21",
      "lot": 20,
      "delta": -0.3381,
      "iv": 24.01,
      "trendAligned": true,
      "capitalReq": 7733,
      "rr": 1.5,
      "winRateEst": 55,
      "vix": 19.95,
      "slTgtMethod": "IV 24% | DTE 3 | Delta 0.34",
      "compositeScore": -0.6,
      "momentumScore": null,
      "emaCross": null,
      "priceZone": "belowPDL",
      "status": "OPEN",
      "exitPrice": null,
      "exitTime": null,
      "pnlPct": null,
      "note": ""
    },
    {
      "id": "2026-05-18-0938-SENSEX-73800-PE",
      "date": "2026-05-18",
      "time": "09:38:19",
      "type": "OPTION",
      "stock": "SENSEX",
      "name": "SENSEX 73800 PE",
      "signal": "BUY",
      "confidence": 84,
      "strength": "STRONG",
      "numInds": 8,
      "entry": 417.45,
      "sl": 292.21,
      "target": 605.31,
      "strike": 73800,
      "optType": "PE",
      "expiry": "2026-05-21",
      "lot": 20,
      "delta": -0.3594,
      "iv": 23.85,
      "trendAligned": true,
      "capitalReq": 8349,
      "rr": 1.5,
      "winRateEst": 55,
      "vix": 19.95,
      "slTgtMethod": "IV 24% | DTE 3 | Delta 0.36",
      "compositeScore": -0.6,
      "momentumScore": null,
      "emaCross": null,
      "priceZone": "belowPDL",
      "status": "OPEN",
      "exitPrice": null,
      "exitTime": null,
      "pnlPct": null,
      "note": ""
    },
    {
      "id": "2026-05-18-0938-SENSEX-73900-PE",
      "date": "2026-05-18",
      "time": "09:38:19",
      "type": "OPTION",
      "stock": "SENSEX",
      "name": "SENSEX 73900 PE",
      "signal": "BUY",
      "confidence": 84,
      "strength": "STRONG",
      "numInds": 8,
      "entry": 450.2,
      "sl": 315.14,
      "target": 652.79,
      "strike": 73900,
      "optType": "PE",
      "expiry": "2026-05-21",
      "lot": 20,
      "delta": -0.3819,
      "iv": 23.78,
      "trendAligned": true,
      "capitalReq": 9004,
      "rr": 1.5,
      "winRateEst": 55,
      "vix": 19.95,
      "slTgtMethod": "IV 24% | DTE 3 | Delta 0.38",
      "compositeScore": -0.6,
      "momentumScore": null,
      "emaCross": null,
      "priceZone": "belowPDL",
      "status": "OPEN",
      "exitPrice": null,
      "exitTime": null,
      "pnlPct": null,
      "note": ""
    },
    {
      "id": "2026-05-18-0938-SENSEX-74000-PE",
      "date": "2026-05-18",
      "time": "09:38:19",
      "type": "OPTION",
      "stock": "SENSEX",
      "name": "SENSEX 74000 PE",
      "signal": "BUY",
      "confidence": 84,
      "strength": "STRONG",
      "numInds": 8,
      "entry": 487.2,
      "sl": 341.04,
      "target": 706.44,
      "strike": 74000,
      "optType": "PE",
      "expiry": "2026-05-21",
      "lot": 20,
      "delta": -0.4041,
      "iv": 23.52,
      "trendAligned": true,
      "capitalReq": 9744,
      "rr": 1.5,
      "winRateEst": 55,
      "vix": 19.95,
      "slTgtMethod": "IV 24% | DTE 3 | Delta 0.40",
      "compositeScore": -0.6,
      "momentumScore": null,
      "emaCross": null,
      "priceZone": "belowPDL",
      "status": "OPEN",
      "exitPrice": null,
      "exitTime": null,
      "pnlPct": null,
      "note": ""
    },
    {
      "id": "2026-05-18-0938-SENSEX-73200-PE",
      "date": "2026-05-18",
      "time": "09:38:19",
      "type": "OPTION",
      "stock": "SENSEX",
      "name": "SENSEX 73200 PE",
      "signal": "WATCH",
      "confidence": 77,
      "strength": "STRONG",
      "numInds": 5,
      "entry": 257.45,
      "sl": 193.09,
      "target": 353.99,
      "strike": 73200,
      "optType": "PE",
      "expiry": "2026-05-21",
      "lot": 20,
      "delta": -0.2448,
      "iv": 24.99,
      "trendAligned": true,
      "capitalReq": 5149,
      "rr": 1.5,
      "winRateEst": 55,
      "vix": 19.95,
      "slTgtMethod": "IV 25% | DTE 3 | Delta 0.24",
      "compositeScore": -0.6,
      "momentumScore": null,
      "emaCross": null,
      "priceZone": "belowPDL",
      "status": "OPEN",
      "exitPrice": null,
      "exitTime": null,
      "pnlPct": null,
      "note": ""
    },
    {
      "id": "2026-05-18-0938-SENSEX-73300-PE",
      "date": "2026-05-18",
      "time": "09:38:19",
      "type": "OPTION",
      "stock": "SENSEX",
      "name": "SENSEX 73300 PE",
      "signal": "WATCH",
      "confidence": 77,
      "strength": "STRONG",
      "numInds": 5,
      "entry": 279.05,
      "sl": 209.29,
      "target": 383.69,
      "strike": 73300,
      "optType": "PE",
      "expiry": "2026-05-21",
      "lot": 20,
      "delta": -0.2614,
      "iv": 24.75,
      "trendAligned": true,
      "capitalReq": 5581,
      "rr": 1.5,
      "winRateEst": 55,
      "vix": 19.95,
      "slTgtMethod": "IV 25% | DTE 3 | Delta 0.26",
      "compositeScore": -0.6,
      "momentumScore": null,
      "emaCross": null,
      "priceZone": "belowPDL",
      "status": "OPEN",
      "exitPrice": null,
      "exitTime": null,
      "pnlPct": null,
      "note": ""
    },
    {
      "id": "2026-05-18-0938-SENSEX-73400-PE",
      "date": "2026-05-18",
      "time": "09:38:19",
      "type": "OPTION",
      "stock": "SENSEX",
      "name": "SENSEX 73400 PE",
      "signal": "WATCH",
      "confidence": 77,
      "strength": "STRONG",
      "numInds": 5,
      "entry": 302.9,
      "sl": 227.17,
      "target": 416.49,
      "strike": 73400,
      "optType": "PE",
      "expiry": "2026-05-21",
      "lot": 20,
      "delta": -0.2793,
      "iv": 24.56,
      "trendAligned": true,
      "capitalReq": 6058,
      "rr": 1.5,
      "winRateEst": 55,
      "vix": 19.95,
      "slTgtMethod": "IV 25% | DTE 3 | Delta 0.28",
      "compositeScore": -0.6,
      "momentumScore": null,
      "emaCross": null,
      "priceZone": "belowPDL",
      "status": "OPEN",
      "exitPrice": null,
      "exitTime": null,
      "pnlPct": null,
      "note": ""
    },
    {
      "id": "2026-05-18-0938-SENSEX-73500-PE",
      "date": "2026-05-18",
      "time": "09:38:19",
      "type": "OPTION",
      "stock": "SENSEX",
      "name": "SENSEX 73500 PE",
      "signal": "WATCH",
      "confidence": 77,
      "strength": "STRONG",
      "numInds": 5,
      "entry": 328.2,
      "sl": 246.15,
      "target": 451.27,
      "strike": 73500,
      "optType": "PE",
      "expiry": "2026-05-21",
      "lot": 20,
      "delta": -0.2984,
      "iv": 24.42,
      "trendAligned": true,
      "capitalReq": 6564,
      "rr": 1.5,
      "winRateEst": 55,
      "vix": 19.95,
      "slTgtMethod": "IV 24% | DTE 3 | Delta 0.30",
      "compositeScore": -0.6,
      "momentumScore": null,
      "emaCross": null,
      "priceZone": "belowPDL",
      "status": "OPEN",
      "exitPrice": null,
      "exitTime": null,
      "pnlPct": null,
      "note": ""
    },
    {
      "id": "2026-05-18-0938-SENSEX-72600-PE",
      "date": "2026-05-18",
      "time": "09:38:19",
      "type": "OPTION",
      "stock": "SENSEX",
      "name": "SENSEX 72600 PE",
      "signal": "WATCH",
      "confidence": 74,
      "strength": "MODERATE",
      "numInds": 5,
      "entry": 154.45,
      "sl": 115.84,
      "target": 212.36,
      "strike": 72600,
      "optType": "PE",
      "expiry": "2026-05-21",
      "lot": 20,
      "delta": -0.1588,
      "iv": 26.04,
      "trendAligned": true,
      "capitalReq": 3089,
      "rr": 1.5,
      "winRateEst": 55,
      "vix": 19.95,
      "slTgtMethod": "IV 26% | DTE 3 | Delta 0.16",
      "compositeScore": -0.6,
      "momentumScore": null,
      "emaCross": null,
      "priceZone": "belowPDL",
      "status": "OPEN",
      "exitPrice": null,
      "exitTime": null,
      "pnlPct": null,
      "note": ""
    },
    {
      "id": "2026-05-18-0938-SENSEX-72700-PE",
      "date": "2026-05-18",
      "time": "09:38:19",
      "type": "OPTION",
      "stock": "SENSEX",
      "name": "SENSEX 72700 PE",
      "signal": "WATCH",
      "confidence": 74,
      "strength": "MODERATE",
      "numInds": 5,
      "entry": 168.5,
      "sl": 126.38,
      "target": 231.68,
      "strike": 72700,
      "optType": "PE",
      "expiry": "2026-05-21",
      "lot": 20,
      "delta": -0.171,
      "iv": 25.85,
      "trendAligned": true,
      "capitalReq": 3370,
      "rr": 1.5,
      "winRateEst": 55,
      "vix": 19.95,
      "slTgtMethod": "IV 26% | DTE 3 | Delta 0.17",
      "compositeScore": -0.6,
      "momentumScore": null,
      "emaCross": null,
      "priceZone": "belowPDL",
      "status": "OPEN",
      "exitPrice": null,
      "exitTime": null,
      "pnlPct": null,
      "note": ""
    },
    {
      "id": "2026-05-18-0938-SENSEX-72800-PE",
      "date": "2026-05-18",
      "time": "09:38:19",
      "type": "OPTION",
      "stock": "SENSEX",
      "name": "SENSEX 72800 PE",
      "signal": "WATCH",
      "confidence": 74,
      "strength": "MODERATE",
      "numInds": 5,
      "entry": 183.2,
      "sl": 137.4,
      "target": 251.9,
      "strike": 72800,
      "optType": "PE",
      "expiry": "2026-05-21",
      "lot": 20,
      "delta": -0.1841,
      "iv": 25.67,
      "trendAligned": true,
      "capitalReq": 3664,
      "rr": 1.5,
      "winRateEst": 55,
      "vix": 19.95,
      "slTgtMethod": "IV 26% | DTE 3 | Delta 0.18",
      "compositeScore": -0.6,
      "momentumScore": null,
      "emaCross": null,
      "priceZone": "belowPDL",
      "status": "OPEN",
      "exitPrice": null,
      "exitTime": null,
      "pnlPct": null,
      "note": ""
    },
    {
      "id": "2026-05-18-0938-SENSEX-72900-PE",
      "date": "2026-05-18",
      "time": "09:38:19",
      "type": "OPTION",
      "stock": "SENSEX",
      "name": "SENSEX 72900 PE",
      "signal": "WATCH",
      "confidence": 74,
      "strength": "MODERATE",
      "numInds": 5,
      "entry": 199.4,
      "sl": 149.55,
      "target": 274.18,
      "strike": 72900,
      "optType": "PE",
      "expiry": "2026-05-21",
      "lot": 20,
      "delta": -0.198,
      "iv": 25.49,
      "trendAligned": true,
      "capitalReq": 3988,
      "rr": 1.5,
      "winRateEst": 55,
      "vix": 19.95,
      "slTgtMethod": "IV 25% | DTE 3 | Delta 0.20",
      "compositeScore": -0.6,
      "momentumScore": null,
      "emaCross": null,
      "priceZone": "belowPDL",
      "status": "OPEN",
      "exitPrice": null,
      "exitTime": null,
      "pnlPct": null,
      "note": ""
    },
    {
      "id": "2026-05-18-0938-SENSEX-73000-PE",
      "date": "2026-05-18",
      "time": "09:38:19",
      "type": "OPTION",
      "stock": "SENSEX",
      "name": "SENSEX 73000 PE",
      "signal": "WATCH",
      "confidence": 74,
      "strength": "MODERATE",
      "numInds": 5,
      "entry": 216.95,
      "sl": 162.71,
      "target": 298.31,
      "strike": 73000,
      "optType": "PE",
      "expiry": "2026-05-21",
      "lot": 20,
      "delta": -0.2128,
      "iv": 25.33,
      "trendAligned": true,
      "capitalReq": 4339,
      "rr": 1.5,
      "winRateEst": 55,
      "vix": 19.95,
      "slTgtMethod": "IV 25% | DTE 3 | Delta 0.21",
      "compositeScore": -0.6,
      "momentumScore": null,
      "emaCross": null,
      "priceZone": "belowPDL",
      "status": "OPEN",
      "exitPrice": null,
      "exitTime": null,
      "pnlPct": null,
      "note": ""
    },
    {
      "id": "2026-05-18-0938-SENSEX-73100-PE",
      "date": "2026-05-18",
      "time": "09:38:19",
      "type": "OPTION",
      "stock": "SENSEX",
      "name": "SENSEX 73100 PE",
      "signal": "WATCH",
      "confidence": 74,
      "strength": "MODERATE",
      "numInds": 5,
      "entry": 237.25,
      "sl": 177.94,
      "target": 326.22,
      "strike": 73100,
      "optType": "PE",
      "expiry": "2026-05-21",
      "lot": 20,
      "delta": -0.2287,
      "iv": 25.19,
      "trendAligned": true,
      "capitalReq": 4745,
      "rr": 1.5,
      "winRateEst": 55,
      "vix": 19.95,
      "slTgtMethod": "IV 25% | DTE 3 | Delta 0.23",
      "compositeScore": -0.6,
      "momentumScore": null,
      "emaCross": null,
      "priceZone": "belowPDL",
      "status": "OPEN",
      "exitPrice": null,
      "exitTime": null,
      "pnlPct": null,
      "note": ""
    },
    {
      "id": "2026-05-18-0938-FINNIFTY-24950-PE",
      "date": "2026-05-18",
      "time": "09:38:19",
      "type": "OPTION",
      "stock": "FINNIFTY",
      "name": "FINNIFTY 24950 PE",
      "signal": "BUY",
      "confidence": 85,
      "strength": "STRONG",
      "numInds": 6,
      "entry": 129,
      "sl": 90.3,
      "target": 200.6,
      "strike": 24950,
      "optType": "PE",
      "expiry": "2026-05-26",
      "lot": 65,
      "delta": -0.4062,
      "iv": 11.64,
      "trendAligned": true,
      "capitalReq": 8385,
      "rr": 1.85,
      "winRateEst": 55,
      "vix": 19.95,
      "slTgtMethod": "IV 12% | DTE 8 | Delta 0.41",
      "compositeScore": -0.6,
      "momentumScore": null,
      "emaCross": null,
      "priceZone": "belowPDL",
      "status": "OPEN",
      "exitPrice": null,
      "exitTime": null,
      "pnlPct": null,
      "note": ""
    },
    {
      "id": "2026-05-18-0938-FINNIFTY-24750-PE",
      "date": "2026-05-18",
      "time": "09:38:19",
      "type": "OPTION",
      "stock": "FINNIFTY",
      "name": "FINNIFTY 24750 PE",
      "signal": "BUY",
      "confidence": 84,
      "strength": "STRONG",
      "numInds": 8,
      "entry": 127.2,
      "sl": 95.4,
      "target": 181.26,
      "strike": 24750,
      "optType": "PE",
      "expiry": "2026-05-26",
      "lot": 65,
      "delta": -0.3109,
      "iv": 16.68,
      "trendAligned": true,
      "capitalReq": 8268,
      "rr": 1.7,
      "winRateEst": 55,
      "vix": 19.95,
      "slTgtMethod": "IV 17% | DTE 8 | Delta 0.31",
      "compositeScore": -0.6,
      "momentumScore": null,
      "emaCross": null,
      "priceZone": "belowPDL",
      "status": "OPEN",
      "exitPrice": null,
      "exitTime": null,
      "pnlPct": null,
      "note": ""
    },
    {
      "id": "2026-05-18-0938-FINNIFTY-24800-PE",
      "date": "2026-05-18",
      "time": "09:38:19",
      "type": "OPTION",
      "stock": "FINNIFTY",
      "name": "FINNIFTY 24800 PE",
      "signal": "BUY",
      "confidence": 84,
      "strength": "STRONG",
      "numInds": 8,
      "entry": 138.85,
      "sl": 104.14,
      "target": 203.06,
      "strike": 24800,
      "optType": "PE",
      "expiry": "2026-05-26",
      "lot": 65,
      "delta": -0.3367,
      "iv": 16.31,
      "trendAligned": true,
      "capitalReq": 9025,
      "rr": 1.85,
      "winRateEst": 55,
      "vix": 19.95,
      "slTgtMethod": "IV 16% | DTE 8 | Delta 0.34",
      "compositeScore": -0.6,
      "momentumScore": null,
      "emaCross": null,
      "priceZone": "belowPDL",
      "status": "OPEN",
      "exitPrice": null,
      "exitTime": null,
      "pnlPct": null,
      "note": ""
    },
    {
      "id": "2026-05-18-0938-FINNIFTY-24250-PE",
      "date": "2026-05-18",
      "time": "09:38:19",
      "type": "OPTION",
      "stock": "FINNIFTY",
      "name": "FINNIFTY 24250 PE",
      "signal": "WATCH",
      "confidence": 77,
      "strength": "STRONG",
      "numInds": 5,
      "entry": 80.35,
      "sl": 60.26,
      "target": 114.5,
      "strike": 24250,
      "optType": "PE",
      "expiry": "2026-05-26",
      "lot": 65,
      "delta": -0.1692,
      "iv": 23.23,
      "trendAligned": true,
      "capitalReq": 5223,
      "rr": 1.7,
      "winRateEst": 55,
      "vix": 19.95,
      "slTgtMethod": "IV 23% | DTE 8 | Delta 0.17",
      "compositeScore": -0.6,
      "momentumScore": null,
      "emaCross": null,
      "priceZone": "belowPDL",
      "status": "OPEN",
      "exitPrice": null,
      "exitTime": null,
      "pnlPct": null,
      "note": ""
    },
    {
      "id": "2026-05-18-0938-FINNIFTY-24450-PE",
      "date": "2026-05-18",
      "time": "09:38:19",
      "type": "OPTION",
      "stock": "FINNIFTY",
      "name": "FINNIFTY 24450 PE",
      "signal": "WATCH",
      "confidence": 77,
      "strength": "STRONG",
      "numInds": 5,
      "entry": 101.65,
      "sl": 76.24,
      "target": 144.85,
      "strike": 24450,
      "optType": "PE",
      "expiry": "2026-05-26",
      "lot": 65,
      "delta": -0.2155,
      "iv": 21.61,
      "trendAligned": true,
      "capitalReq": 6607,
      "rr": 1.7,
      "winRateEst": 55,
      "vix": 19.95,
      "slTgtMethod": "IV 22% | DTE 8 | Delta 0.22",
      "compositeScore": -0.6,
      "momentumScore": null,
      "emaCross": null,
      "priceZone": "belowPDL",
      "status": "OPEN",
      "exitPrice": null,
      "exitTime": null,
      "pnlPct": null,
      "note": ""
    },
    {
      "id": "2026-05-18-0938-FINNIFTY-24650-PE",
      "date": "2026-05-18",
      "time": "09:38:19",
      "type": "OPTION",
      "stock": "FINNIFTY",
      "name": "FINNIFTY 24650 PE",
      "signal": "WATCH",
      "confidence": 77,
      "strength": "STRONG",
      "numInds": 5,
      "entry": 108.7,
      "sl": 81.53,
      "target": 154.89,
      "strike": 24650,
      "optType": "PE",
      "expiry": "2026-05-26",
      "lot": 65,
      "delta": -0.2665,
      "iv": 17.55,
      "trendAligned": true,
      "capitalReq": 7066,
      "rr": 1.7,
      "winRateEst": 55,
      "vix": 19.95,
      "slTgtMethod": "IV 18% | DTE 8 | Delta 0.27",
      "compositeScore": -0.6,
      "momentumScore": null,
      "emaCross": null,
      "priceZone": "belowPDL",
      "status": "OPEN",
      "exitPrice": null,
      "exitTime": null,
      "pnlPct": null,
      "note": ""
    },
    {
      "id": "2026-05-18-0938-FINNIFTY-24200-PE",
      "date": "2026-05-18",
      "time": "09:38:19",
      "type": "OPTION",
      "stock": "FINNIFTY",
      "name": "FINNIFTY 24200 PE",
      "signal": "WATCH",
      "confidence": 75,
      "strength": "STRONG",
      "numInds": 5,
      "entry": 69.95,
      "sl": 52.46,
      "target": 99.68,
      "strike": 24200,
      "optType": "PE",
      "expiry": "2026-05-26",
      "lot": 65,
      "delta": -0.1535,
      "iv": 22.87,
      "trendAligned": true,
      "capitalReq": 4547,
      "rr": 1.7,
      "winRateEst": 55,
      "vix": 19.95,
      "slTgtMethod": "IV 23% | DTE 8 | Delta 0.15",
      "compositeScore": -0.6,
      "momentumScore": null,
      "emaCross": null,
      "priceZone": "belowPDL",
      "status": "OPEN",
      "exitPrice": null,
      "exitTime": null,
      "pnlPct": null,
      "note": ""
    },
    {
      "id": "2026-05-18-0938-FINNIFTY-24050-PE",
      "date": "2026-05-18",
      "time": "09:38:19",
      "type": "OPTION",
      "stock": "FINNIFTY",
      "name": "FINNIFTY 24050 PE",
      "signal": "WATCH",
      "confidence": 73,
      "strength": "MODERATE",
      "numInds": 5,
      "entry": 34.4,
      "sl": 25.8,
      "target": 49.02,
      "strike": 24050,
      "optType": "PE",
      "expiry": "2026-05-26",
      "lot": 65,
      "delta": -0.0931,
      "iv": 20.75,
      "trendAligned": true,
      "capitalReq": 2236,
      "rr": 1.7,
      "winRateEst": 55,
      "vix": 19.95,
      "slTgtMethod": "IV 21% | DTE 8 | Delta 0.09",
      "compositeScore": -0.6,
      "momentumScore": null,
      "emaCross": null,
      "priceZone": "belowPDL",
      "status": "OPEN",
      "exitPrice": null,
      "exitTime": null,
      "pnlPct": null,
      "note": ""
    },
    {
      "id": "2026-05-18-0938-FINNIFTY-24150-PE",
      "date": "2026-05-18",
      "time": "09:38:19",
      "type": "OPTION",
      "stock": "FINNIFTY",
      "name": "FINNIFTY 24150 PE",
      "signal": "WATCH",
      "confidence": 73,
      "strength": "MODERATE",
      "numInds": 5,
      "entry": 27.55,
      "sl": 20.66,
      "target": 39.26,
      "strike": 24150,
      "optType": "PE",
      "expiry": "2026-05-26",
      "lot": 65,
      "delta": -0.0878,
      "iv": 17.87,
      "trendAligned": true,
      "capitalReq": 1791,
      "rr": 1.7,
      "winRateEst": 55,
      "vix": 19.95,
      "slTgtMethod": "IV 18% | DTE 8 | Delta 0.09",
      "compositeScore": -0.6,
      "momentumScore": null,
      "emaCross": null,
      "priceZone": "belowPDL",
      "status": "OPEN",
      "exitPrice": null,
      "exitTime": null,
      "pnlPct": null,
      "note": ""
    },
    {
      "id": "2026-05-18-0938-FINNIFTY-23600-PE",
      "date": "2026-05-18",
      "time": "09:38:19",
      "type": "OPTION",
      "stock": "FINNIFTY",
      "name": "FINNIFTY 23600 PE",
      "signal": "SELL",
      "confidence": 71,
      "strength": "MODERATE",
      "numInds": 4,
      "entry": 30.6,
      "sl": 38.25,
      "target": 17.59,
      "strike": 23600,
      "optType": "PE",
      "expiry": "2026-05-26",
      "lot": 65,
      "delta": -0.0673,
      "iv": 27.04,
      "trendAligned": true,
      "capitalReq": 1989,
      "rr": 1.7,
      "winRateEst": 55,
      "vix": 19.95,
      "slTgtMethod": "IV 27% | DTE 8 | Delta 0.07 · SELL (flipped)",
      "compositeScore": -0.6,
      "momentumScore": null,
      "emaCross": null,
      "priceZone": "belowPDL",
      "status": "OPEN",
      "exitPrice": null,
      "exitTime": null,
      "pnlPct": null,
      "note": ""
    },
    {
      "id": "2026-05-18-0938-FINNIFTY-23650-PE",
      "date": "2026-05-18",
      "time": "09:38:19",
      "type": "OPTION",
      "stock": "FINNIFTY",
      "name": "FINNIFTY 23650 PE",
      "signal": "SELL",
      "confidence": 71,
      "strength": "MODERATE",
      "numInds": 4,
      "entry": 31.15,
      "sl": 38.94,
      "target": 17.91,
      "strike": 23650,
      "optType": "PE",
      "expiry": "2026-05-26",
      "lot": 65,
      "delta": -0.0701,
      "iv": 26.29,
      "trendAligned": true,
      "capitalReq": 2025,
      "rr": 1.7,
      "winRateEst": 55,
      "vix": 19.95,
      "slTgtMethod": "IV 26% | DTE 8 | Delta 0.07 · SELL (flipped)",
      "compositeScore": -0.6,
      "momentumScore": null,
      "emaCross": null,
      "priceZone": "belowPDL",
      "status": "OPEN",
      "exitPrice": null,
      "exitTime": null,
      "pnlPct": null,
      "note": ""
    }
  ],
  "lastUpdated": "2026-05-18T04:08:28.103Z",
  "upstoxId": "132199",
  "stats": {
    "total": 33,
    "hits": 0,
    "sls": 0,
    "open": 33,
    "winRate": null,
    "avgConf": 78
  }
}