{
  "signals": [
    {
      "id": "2026-05-21-0804-ZEEL-BO",
      "date": "2026-05-21",
      "time": "08:04:38",
      "type": "STOCK",
      "source": "BREAKOUT",
      "breakoutType": "PDL_BREAK",
      "stock": "ZEEL",
      "instrKey": "NSE_EQ|INE256A01028",
      "name": "Zee Entertainment Enterprises Limited",
      "signal": "SELL",
      "confidence": 60,
      "strength": "MODERATE",
      "entry": 82.95,
      "sl": 88.9,
      "target": 71.05,
      "rr": 2,
      "status": "OPEN",
      "exitPrice": null,
      "exitTime": null,
      "pnlPct": null,
      "boScore": 6,
      "sector": "Media Entertainment & Publication",
      "volRatio": 1.95,
      "wk52pos": 17.9,
      "phase": "pre"
    }
  ],
  "lastUpdated": "2026-05-21T02:34:39.739Z",
  "upstoxId": "132199",
  "stats": {
    "total": 1,
    "hits": 0,
    "sls": 0,
    "open": 1,
    "winRate": null,
    "avgConf": 60
  }
}